main.py
aoc_quick_templater-0.1.5.dist-info/METADATA
aoc_quick_templater-0.1.5.dist-info/WHEEL
aoc_quick_templater-0.1.5.dist-info/entry_points.txt
aoc_quick_templater-0.1.5.dist-info/top_level.txt
aoc_quick_templater-0.1.5.dist-info/RECORD
