Metadata-Version: 2.1
Name: aoc-quick-templater
Version: 0.1.5
Summary: Templates AoC problem in python
License: MIT License
Requires-Python: >=3.12
Requires-Dist: httpx>=0.28.0
Requires-Dist: jinja2>=3.1.4
Requires-Dist: typer>=0.14.0
